ansibleroler/__init__.py
ansibleroler/__main__.py
ansibleroler/static/config/logging.yml
ansibleroler/static/templates/main.yml.j2
ansibleroler/utils/__init__.py
ansibleroler/utils/settings.py
ansibleroler/utils/template.py
ansible_roler-0.2.3.dist-info/LICENSE
ansible_roler-0.2.3.dist-info/METADATA
ansible_roler-0.2.3.dist-info/WHEEL
ansible_roler-0.2.3.dist-info/entry_points.txt
ansible_roler-0.2.3.dist-info/top_level.txt
ansible_roler-0.2.3.dist-info/RECORD
