Metadata-Version: 2.1
Name: ansible-roler
Version: 0.2.3
Summary: Command line tool to template the structure of a new ansible role.
Home-page: https://github.com/xoxys/ansible-role
Author: Robert Kaussow
Author-email: mail@geeklabor.de
License: MIT
Keywords: ansible cli role template
Platform: UNKNOWN
Classifier: Development Status :: 5 - Production/Stable
Classifier: Environment :: Console
Classifier: License :: OSI Approved :: MIT License
Classifier: Intended Audience :: Developers
Classifier: Intended Audience :: Information Technology
Classifier: Intended Audience :: System Administrators
Classifier: Natural Language :: English
Classifier: Operating System :: POSIX
Classifier: Programming Language :: Python :: 2
Classifier: Programming Language :: Python :: 2.7
Classifier: Programming Language :: Python :: 3
Classifier: Programming Language :: Python :: 3.4
Classifier: Programming Language :: Python :: 3.5
Classifier: Programming Language :: Python :: 3.6
Classifier: Programming Language :: Python :: 3.7
Classifier: Topic :: Utilities
Requires-Python: >=2.7,!=3.0.*,!=3.1.*,!=3.2.*,!=3.3.*
Requires-Dist: six
Requires-Dist: appdirs
Requires-Dist: jinja2
Requires-Dist: PyYAML
Requires-Dist: configparser
